cli/__init__.py
cli/surx.py
surframe/__init__.py
surframe/advise.py
surframe/audit.py
surframe/crypto.py
surframe/io.py
surframe/license.py
surframe/manifest.py
surframe/plugins.py
surframe/security.py
surframe/ann/__init__.py
surframe/ann/flat.py
surframe/formats/csv_detect.py
surframe/formats/json_deep.py
surframe/indexes/__init__.py
surframe/indexes/ann.py
surframe/indexes/bloom.py
surframe/indexes/hll.py
surframe/indexes/minmax.py
surframe/sf_codecs/__init__.py
surframe/sf_codecs/cat.py
surframe/sf_codecs/num.py
surframe/sf_codecs/ts.py
surframe-0.1.5.dist-info/licenses/LICENSE
surframe-0.1.5.dist-info/licenses/NOTICE
surframe-0.1.5.dist-info/METADATA
surframe-0.1.5.dist-info/WHEEL
surframe-0.1.5.dist-info/entry_points.txt
surframe-0.1.5.dist-info/top_level.txt
surframe-0.1.5.dist-info/RECORD
